{
  "date": "11/12/2025",
  "gold": 12050,
  "silver": 209,
  "sma7_gold": 12025.71,
  "sma20_gold": 11853.5,
  "sma30_gold": 11749.33,
  "ema12_gold": 11970.62,
  "ema26_gold": 11825.12,
  "macd_gold": 145.5,
  "macd_signal_gold": 146.34,
  "macd_hist_gold": -0.84,
  "rsi14_gold": 75.38,
  "boll_sma20_gold": NaN,
  "boll_upper_gold": 12299.31,
  "boll_lower_gold": 11407.69,
  "sma7_silver": 201.14,
  "sma20_silver": 188.2,
  "sma30_silver": 182.8,
  "ema12_silver": 197.23,
  "ema26_silver": 188.75,
  "macd_silver": 8.48,
  "macd_signal_silver": 6.78,
  "macd_hist_silver": 1.7,
  "rsi14_silver": 87.23,
  "boll_sma20_silver": NaN,
  "boll_upper_silver": 215.15,
  "boll_lower_silver": 161.25
}