{
  "date": "14/03/2026",
  "gold": 14760,
  "silver": 280,
  "sma7_gold": 14971.43,
  "sma20_gold": 15077.25,
  "sma30_gold": 14873.17,
  "ema12_gold": 14999.14,
  "ema26_gold": 14909.99,
  "macd_gold": 89.15,
  "macd_signal_gold": 165.33,
  "macd_hist_gold": -76.18,
  "rsi14_gold": 47.1,
  "boll_sma20_gold": NaN,
  "boll_upper_gold": 15672.17,
  "boll_lower_gold": 14482.33,
  "sma7_silver": 291.43,
  "sma20_silver": 297.0,
  "sma30_silver": 291.0,
  "ema12_silver": 292.77,
  "ema26_silver": 295.28,
  "macd_silver": -2.52,
  "macd_signal_silver": -1.34,
  "macd_hist_silver": -1.18,
  "rsi14_silver": 42.11,
  "boll_sma20_silver": NaN,
  "boll_upper_silver": 318.13,
  "boll_lower_silver": 275.87
}